log_manager/__init__.py
log_manager/main.py
log_manager-1.0.1.dist-info/LICENSE
log_manager-1.0.1.dist-info/METADATA
log_manager-1.0.1.dist-info/WHEEL
log_manager-1.0.1.dist-info/top_level.txt
log_manager-1.0.1.dist-info/RECORD
